hyprmonmon.py
hyprmonmon-0.1.0.dist-info/METADATA
hyprmonmon-0.1.0.dist-info/WHEEL
hyprmonmon-0.1.0.dist-info/entry_points.txt
hyprmonmon-0.1.0.dist-info/licenses/LICENSE.txt
hyprmonmon-0.1.0.dist-info/RECORD
