Metadata-Version: 2.4
Name: hyprmonmon
Version: 0.1.0
Summary: Automatically manage multiple monitor setups for hyprland
License: MIT
License-File: LICENSE.txt
Author: Ingmar Steen
Author-email: iksteen@gmail.com
Requires-Python: >=3.12
Classifier: License :: OSI Approved :: MIT License
Classifier: Programming Language :: Python :: 3
Classifier: Programming Language :: Python :: 3.12
Classifier: Programming Language :: Python :: 3.13
Classifier: Programming Language :: Python :: 3.14
Requires-Dist: click (>=8.2.1,<9.0.0)
Requires-Dist: hyprpy (>=0.2.0,<0.3.0)
